protovalidate/__init__.py
protovalidate/py.typed
protovalidate/validator.py
protovalidate/internal/__init__.py
protovalidate/internal/cel_field_presence.py
protovalidate/internal/extra_func.py
protovalidate/internal/rules.py
protovalidate/internal/string_format.py
protovalidate-1.0.0.dist-info/METADATA
protovalidate-1.0.0.dist-info/WHEEL
protovalidate-1.0.0.dist-info/licenses/LICENSE
protovalidate-1.0.0.dist-info/RECORD
