Metadata-Version: 2.4
Name: protovalidate
Version: 1.0.0
Summary: Protocol Buffer Validation for Python
Project-URL: Homepage, https://github.com/bufbuild/protovalidate-python
Project-URL: Source, https://github.com/bufbuild/protovalidate-python
Project-URL: Issues, https://github.com/bufbuild/protovalidate-python/issues
License-Expression: Apache-2.0
License-File: LICENSE
Keywords: protobuf,protocol buffer,validate
Classifier: Operating System :: OS Independent
Classifier: Programming Language :: Python :: 3.9
Classifier: Programming Language :: Python :: 3.10
Classifier: Programming Language :: Python :: 3.11
Classifier: Programming Language :: Python :: 3.12
Classifier: Programming Language :: Python :: 3.13
Classifier: Typing :: Typed
Requires-Python: >=3.9
Requires-Dist: cel-python==0.2.*
Requires-Dist: google-re2>=1
Requires-Dist: google-re2>=1.1.20250722; python_version == '3.13'
Requires-Dist: google-re2>=1.1; python_version == '3.12'
Requires-Dist: protobuf>=5
